<?xml version="1.0" encoding="UTF-8" standalone="yes"?>
<app version="1">
<name>Configurable USB Loader</name>
<version>unknown</version>
<release_date>unknown</release_date>
<coder>oggzee, usptactical, gannon, Clipper, ...</coder>
<short_description>Play from USB drive</short_description>
<long_description>
Play Wii Backups from USB harddrive
Waninkoko cIOS 249 is supported.
Hermes cIOS 222/223 is supported.
USE AT YOUR OWN RISK!
</long_description>
<arguments>
<arg>ios = 248</arg>
</arguments></app>
